pybuf.py
pybuf-1.1.1.dist-info/DESCRIPTION.rst
pybuf-1.1.1.dist-info/METADATA
pybuf-1.1.1.dist-info/RECORD
pybuf-1.1.1.dist-info/WHEEL
pybuf-1.1.1.dist-info/metadata.json
pybuf-1.1.1.dist-info/top_level.txt
