Metadata-Version: 2.0
Name: pybuf
Version: 1.1.1
Summary: Modularize Protocol Buffer Compiler generated code for use within your package
Home-page: https://github.com/mdmedley/pybuf
Author: Marcus Medley
Author-email: mdmeds@gmail.com
License: MIT
Platform: UNKNOWN
Classifier: Programming Language :: Python :: 2
Classifier: Intended Audience :: Developers
Classifier: Natural Language :: English
Classifier: License :: OSI Approved :: MIT License
Classifier: Topic :: Software Development :: Libraries
Classifier: Topic :: Utilities
Requires-Dist: protobuf
